README.txt
setup.cfg
setup.py
collective/__init__.py
collective.alerts.egg-info/PKG-INFO
collective.alerts.egg-info/SOURCES.txt
collective.alerts.egg-info/dependency_links.txt
collective.alerts.egg-info/entry_points.txt
collective.alerts.egg-info/namespace_packages.txt
collective.alerts.egg-info/not-zip-safe
collective.alerts.egg-info/requires.txt
collective.alerts.egg-info/top_level.txt
collective/alerts/__init__.py
collective/alerts/config.py
collective/alerts/configure.zcml
collective/alerts/interfaces.py
collective/alerts/setuphandlers.py
collective/alerts/browser/__init__.py
collective/alerts/browser/config.py
collective/alerts/browser/configure.zcml
collective/alerts/browser/interfaces.py
collective/alerts/browser/resources/help.gif
collective/alerts/browser/resources/important.gif
collective/alerts/browser/resources/info.gif
collective/alerts/browser/resources/jquery.alerts.css
collective/alerts/browser/resources/jquery.alerts.css~
collective/alerts/browser/resources/jquery.alerts.js
collective/alerts/browser/resources/jquery.alerts.js~
collective/alerts/browser/resources/title.gif
collective/alerts/profiles/default/actionicons.xml
collective/alerts/profiles/default/collective.js.alerts_marker.txt
collective/alerts/profiles/default/controlpanel.xml
collective/alerts/profiles/default/cssregistry.xml
collective/alerts/profiles/default/jsregistry.xml
collective/alerts/profiles/default/metadata.xml
docs/HISTORY.txt