Metadata-Version: 1.0
Name: collective.alerts
Version: 1.2.3
Summary: Implements Cory LaViska's JQuery Alerts feature for Plone
Home-page: http://svn.plone.org/svn/collective/collective.alerts
Author: JC Brand, Cory LaViska
Author-email: jc@opkode.com
License: GPL
Keywords: plone jquery alerts
Platform: UNKNOWN
Classifier: Programming Language :: Python
Classifier: Topic :: Software Development :: Libraries :: Python Modules
